{"cameraMode":{"drawMode":0,"name":"Shaded","section":"Shading Mode"},"sceneLighting":true,"audioPlay":false,"sceneViewState":{"showFog":true,"showMaterialUpdate":false,"showSkybox":true,"showFlares":true,"showImageEffects":true,"showParticleSystems":true},"in2DMode":false,"pivot":{"x":2.323413372039795,"y":1.6835577487945557,"z":29.87715721130371},"rotation":{"x":-0.027278196066617967,"y":-0.0458703450858593,"z":0.001248933607712388,"w":-0.9985930919647217},"size":16.440879821777345,"orthographic":false}